fastapi_crud_kit/__init__.py
fastapi_crud_kit/crud/__init__.py
fastapi_crud_kit/crud/base.py
fastapi_crud_kit/crud/manager/__init__.py
fastapi_crud_kit/crud/manager/async_manager.py
fastapi_crud_kit/crud/manager/base.py
fastapi_crud_kit/crud/manager/sync_manager.py
fastapi_crud_kit/database/__init__.py
fastapi_crud_kit/database/base.py
fastapi_crud_kit/database/context/__init__.py
fastapi_crud_kit/database/context/read_only.py
fastapi_crud_kit/database/context/retry.py
fastapi_crud_kit/database/context/timeout.py
fastapi_crud_kit/database/context/transaction.py
fastapi_crud_kit/database/context/utils.py
fastapi_crud_kit/database/exceptions.py
fastapi_crud_kit/database/factory.py
fastapi_crud_kit/database/mode/__init__.py
fastapi_crud_kit/database/mode/async_mode.py
fastapi_crud_kit/database/mode/base.py
fastapi_crud_kit/database/mode/sync_mode.py
fastapi_crud_kit/database/session.py
fastapi_crud_kit/models/__init__.py
fastapi_crud_kit/models/base.py
fastapi_crud_kit/models/mixins.py
fastapi_crud_kit/query/__init__.py
fastapi_crud_kit/query/builder.py
fastapi_crud_kit/query/config.py
fastapi_crud_kit/query/exceptions.py
fastapi_crud_kit/query/fields/__init__.py
fastapi_crud_kit/query/fields/allowed.py
fastapi_crud_kit/query/fields/validator.py
fastapi_crud_kit/query/filters/__init__.py
fastapi_crud_kit/query/filters/allowed.py
fastapi_crud_kit/query/filters/operators.py
fastapi_crud_kit/query/filters/parser.py
fastapi_crud_kit/query/filters/validator.py
fastapi_crud_kit/query/include/__init__.py
fastapi_crud_kit/query/include/allowed.py
fastapi_crud_kit/query/include/validator.py
fastapi_crud_kit/query/parser.py
fastapi_crud_kit/query/schema.py
fastapi_crud_kit/query/sort/__init__.py
fastapi_crud_kit/query/sort/allowed.py
fastapi_crud_kit/query/sort/validator.py
fastapi_crud_kit/query/utils.py
fastapi_crud_kit-0.2.0.dist-info/METADATA
fastapi_crud_kit-0.2.0.dist-info/WHEEL
fastapi_crud_kit-0.2.0.dist-info/licenses/LICENSE
fastapi_crud_kit-0.2.0.dist-info/RECORD
