Metadata-Version: 2.4
Name: fastapi-crud-kit
Version: 0.2.0
Summary: A powerful CRUD toolkit for FastAPI with SQLAlchemy, featuring query building, filtering, sorting, and field selection with async/sync support.
License-File: LICENSE
Author: Ephraim Seddor
Author-email: seddorephraim7@gmail.com
Requires-Python: >=3.10,<4.0
Classifier: Programming Language :: Python :: 3
Classifier: Programming Language :: Python :: 3.10
Classifier: Programming Language :: Python :: 3.11
Classifier: Programming Language :: Python :: 3.12
Classifier: Programming Language :: Python :: 3.13
Classifier: Programming Language :: Python :: 3.14
Requires-Dist: fastapi (>=0.128.0,<0.130.0)
Requires-Dist: pydantic (>=2.12.5,<3.0.0)
Requires-Dist: sqlalchemy (>=2.0.45,<3.0.0)
